racetools/__init__.py
racetools/errors.py
racetools/telemetry/__init__.py
racetools/telemetry/pcars/__init__.py
racetools/telemetry/pcars/udp.py
racetools/util/__init__.py
racetools/util/types.py
racetools-0.1.dev0.dist-info/WHEEL
racetools-0.1.dev0.dist-info/METADATA
racetools-0.1.dev0.dist-info/RECORD
