Metadata-Version: 2.1
Name: racetools
Version: 0.1.dev0
Summary: A package for retrieving telemetry
Home-page: https://github.com/inkychris/racetools
Author: Chris Wright
Author-email: chris@inkyspider.co.uk
Requires-Python: >=3.9
